.gitignore
.travis.yml
LICENSE
README.md
setup.py
docs/Makefile
docs/make.bat
docs/source/conf.py
docs/source/index.rst
galaxy2galaxy/__init__.py
galaxy2galaxy/problems.py
galaxy2galaxy.egg-info/PKG-INFO
galaxy2galaxy.egg-info/SOURCES.txt
galaxy2galaxy.egg-info/dependency_links.txt
galaxy2galaxy.egg-info/requires.txt
galaxy2galaxy.egg-info/top_level.txt
galaxy2galaxy/bin/concatenate_models.py
galaxy2galaxy/bin/g2g-datagen
galaxy2galaxy/bin/g2g-exporter
galaxy2galaxy/bin/g2g-trainer
galaxy2galaxy/data_generators/__init__.py
galaxy2galaxy/data_generators/all_problems.py
galaxy2galaxy/data_generators/astroimage_utils.py
galaxy2galaxy/data_generators/cosmos.py
galaxy2galaxy/data_generators/galsim_utils.py
galaxy2galaxy/data_generators/hsc.py
galaxy2galaxy/data_generators/hsc_utils.py
galaxy2galaxy/data_generators/data/hsc_hann_window.fits
galaxy2galaxy/data_generators/data/hsc_pdr2_wide_anomaly.sql
galaxy2galaxy/data_generators/data/hsc_pdr2_wide_anomaly_small.sql
galaxy2galaxy/data_generators/data/hsc_pdr2_wide_img2img.sql
galaxy2galaxy/data_generators/data/hsc_pdr2_wide_photoz.sql
galaxy2galaxy/data_generators/data/hst_cosmos_effective_psf.fits
galaxy2galaxy/layers/__init__.py
galaxy2galaxy/layers/common_layers.py
galaxy2galaxy/layers/flows.py
galaxy2galaxy/layers/image_utils.py
galaxy2galaxy/layers/spectral_ops.py
galaxy2galaxy/layers/tfp_utils.py
galaxy2galaxy/models/__init__.py
galaxy2galaxy/models/autoencoders.py
galaxy2galaxy/models/autoencoders_utils.py
galaxy2galaxy/models/autoregressive.py
galaxy2galaxy/models/gan_utils.py
galaxy2galaxy/models/gans.py
galaxy2galaxy/models/latent_flow.py
galaxy2galaxy/utils/__init__.py
galaxy2galaxy/utils/registry.py
notebooks/AccessingHSCProblems.ipynb
notebooks/BuildingCOSMOS_PSF.ipynb
notebooks/Create_HSC_window.ipynb
notebooks/GeneratingHSCPrior.ipynb
tests/test_generators.py