Metadata-Version: 2.1
Name: galaxy2galaxy
Version: 0.0.1rc5
Summary: Galaxy2Galaxy
Home-page: http://github.com/ml4astro/galaxy2galaxy
Author: ML4Astro Contributors
License: MIT
Keywords: astronomy machine learning
Platform: UNKNOWN
Classifier: Development Status :: 3 - Alpha
Classifier: Intended Audience :: Developers
Classifier: Intended Audience :: Science/Research
Classifier: License :: OSI Approved :: MIT License
Classifier: Topic :: Scientific/Engineering :: Artificial Intelligence
Classifier: Topic :: Scientific/Engineering :: Astronomy
Provides-Extra: tensorflow
Provides-Extra: tensorflow_gpu
Provides-Extra: tensorflow-hub
Provides-Extra: galsim
Provides-Extra: tests
